aiordr/__init__.py
aiordr/client.py
aiordr/exceptions.py
aiordr/helpers.py
aiordr/models/__init__.py
aiordr/models/base.py
aiordr/models/errorcode.py
aiordr/models/events.py
aiordr/models/render.py
aiordr/models/renderserver.py
aiordr/models/skin.py
py.typed
aiordr-0.3.0.dist-info/LICENSE
aiordr-0.3.0.dist-info/METADATA
aiordr-0.3.0.dist-info/WHEEL
aiordr-0.3.0.dist-info/RECORD
