Metadata-Version: 2.1
Name: aiordr
Version: 0.3.0
Summary: Simple and fast library for interacting with the o!rdr API.
Home-page: https://github.com/NiceAesth/aiordr
License: GPLv3+
Keywords: osu!,osu,api
Author: Nice Aesthetics
Author-email: nice@aesth.dev
Requires-Python: >=3.9,<4.0
Classifier: Intended Audience :: Developers
Classifier: License :: OSI Approved :: GNU General Public License v3 or later (GPLv3+)
Classifier: License :: Other/Proprietary License
Classifier: Programming Language :: Python :: 3
Classifier: Programming Language :: Python :: 3.9
Classifier: Programming Language :: Python :: 3.10
Classifier: Programming Language :: Python :: 3.11
Classifier: Programming Language :: Python :: 3.12
Classifier: Typing :: Typed
Provides-Extra: docs
Provides-Extra: test
Requires-Dist: aiohttp (>=3.8.3,<4.0.0)
Requires-Dist: aiolimiter (>=1.0.0,<2.0.0)
Requires-Dist: furo (>=2024.0.0,<2025.0.0) ; extra == "docs"
Requires-Dist: orjson (>=3.8.3,<4.0.0)
Requires-Dist: pydantic (>=2.0.3,<3.0.0)
Requires-Dist: pytest (>=8.0.0,<9.0.0) ; extra == "test"
Requires-Dist: pytest-asyncio (>=0.23.5,<0.24.0) ; extra == "test"
Requires-Dist: pytest-mock (>=3.10.0,<4.0.0) ; extra == "test"
Requires-Dist: python-socketio[asyncio-client] (>=5.7.2,<6.0.0)
Requires-Dist: sphinx (>=7.0.0,<8.0.0) ; extra == "docs"
Requires-Dist: toml (>=0.10.2,<0.11.0) ; extra == "test" or extra == "docs"
Requires-Dist: types-toml (>=0.10.8.1,<0.11.0.0) ; extra == "test"
Project-URL: Documentation, https://aiordr.readthedocs.io/
Project-URL: Repository, https://github.com/NiceAesth/aiordr
